jupyterlab_ai_commands/__init__.py
jupyterlab_ai_commands/_version.py
jupyterlab_ai_commands-0.1.3.data/data/share/jupyter/labextensions/jupyterlab-ai-commands/package.json
jupyterlab_ai_commands-0.1.3.data/data/share/jupyter/labextensions/jupyterlab-ai-commands/schemas/jupyterlab-ai-commands/package.json.orig
jupyterlab_ai_commands-0.1.3.data/data/share/jupyter/labextensions/jupyterlab-ai-commands/schemas/jupyterlab-ai-commands/plugin.json
jupyterlab_ai_commands-0.1.3.data/data/share/jupyter/labextensions/jupyterlab-ai-commands/static/262.b25317c6f7d5220a70b5.js
jupyterlab_ai_commands-0.1.3.data/data/share/jupyter/labextensions/jupyterlab-ai-commands/static/728.fc3fb628b049e57287d7.js
jupyterlab_ai_commands-0.1.3.data/data/share/jupyter/labextensions/jupyterlab-ai-commands/static/remoteEntry.9a4fae4a29d0b9123882.js
jupyterlab_ai_commands-0.1.3.data/data/share/jupyter/labextensions/jupyterlab-ai-commands/static/style.js
jupyterlab_ai_commands-0.1.3.data/data/share/jupyter/labextensions/jupyterlab-ai-commands/static/third-party-licenses.json
jupyterlab_ai_commands-0.1.3.data/data/share/jupyter/labextensions/jupyterlab-ai-commands/install.json
jupyterlab_ai_commands-0.1.3.dist-info/METADATA
jupyterlab_ai_commands-0.1.3.dist-info/WHEEL
jupyterlab_ai_commands-0.1.3.dist-info/licenses/LICENSE
jupyterlab_ai_commands-0.1.3.dist-info/RECORD
