Metadata-Version: 2.4
Name: jupyterlab_ai_commands
Version: 0.1.3
Summary: A set of commands for AI in JupyterLab
Project-URL: Homepage, https://github.com/jupyter-ai-contrib/jupyterlab-ai-commands
Project-URL: Bug Tracker, https://github.com/jupyter-ai-contrib/jupyterlab-ai-commands/issues
Project-URL: Repository, https://github.com/jupyter-ai-contrib/jupyterlab-ai-commands.git
Author: Project Jupyter
License: BSD 3-Clause License
License-File: LICENSE
Keywords: jupyter,jupyterlab,jupyterlab-extension
Classifier: Framework :: Jupyter
Classifier: Framework :: Jupyter :: JupyterLab
Classifier: Framework :: Jupyter :: JupyterLab :: 4
Classifier: Framework :: Jupyter :: JupyterLab :: Extensions
Classifier: Framework :: Jupyter :: JupyterLab :: Extensions :: Prebuilt
Classifier: License :: OSI Approved :: BSD License
Classifier: Programming Language :: Python
Classifier: Programming Language :: Python :: 3
Classifier: Programming Language :: Python :: 3.9
Classifier: Programming Language :: Python :: 3.10
Classifier: Programming Language :: Python :: 3.11
Classifier: Programming Language :: Python :: 3.12
Classifier: Programming Language :: Python :: 3.13
Requires-Python: >=3.9
Requires-Dist: jupyterlab-diff<0.7,>=0.6.0
